<?xml version="1.0" encoding="utf-8"?>
<song><title>出发</title>
<artist>电影原OST</artist>
<p>
	<zh>真的要丢掉昨天的不快乐
	真的要把过去放在角落
	必须 往前走
	必须 学着让自己成熟
	</zh>
	<py>Zhēnde yāo diūdiào zuótiānde bùkuàilè
	Zhēnde yāo bǎguòqù fàngzài jiǎoluò
	Bìxū wǎng qián zǒu
	Bìxū xuézhe ràng zìjǐ chéngshú
	</py>
</p>
<p>
	<zh>有风有雨的路前面还有
	要怎么选择属于我的生活
	站在 原地不动
	或者 叹息年华易老
	</zh>
	<py>Yǒufēng yǒuyǔ delù qiánmiàn háiyǒu
	Yào zěnme xuǎnzé shǔyú wǒde shēnghuó
	Zhàn zàiyuán dì bù dòng
	Huòzhě tànxí niánhuá yì lǎo
	</py>
</p>
<p>
	<zh>出发到另一个新的地方
	生命的过程就像一篇故事
	记着我曾经那样的为你心动
	记着我的梦想我的努力我的真心
	</zh><py>Chūfā dào lìng yīgè xīn de dìfāng
	Shēngmìngde guòchéng jiùxiàng yīpiān gùshì
	Jìzhe wǒ céngjīng nàyàng de wèi nǐ xīndòng
	Jìzhe wǒde mèngxiǎng wǒde nǔlì wǒde zhēnxīn
	</py>
</p>
<p>
	<zh>出发到另一个新的地方
	不能永远抓紧回忆不放
	该面对的总要坦然的去面对
	不该是我的终究还是要让它爱自由</zh>
	<py>Chūfā dào lìng yīgè xīn dì dìfāng
	Bùnéng yǒngyuǎn zhuājǐn huíyì bù fàng
	Gāi miàn duìde zǒngyào tǎnránde qù miànduì
	Bùgāi shì wǒde zhōngjiù háishì yàoràng tā ài zìyóu
	</py>
</p>
<p symbol='repeat' />
</song>